setup.py
recipe_collector/__init__.py
recipe_collector.egg-info/PKG-INFO
recipe_collector.egg-info/SOURCES.txt
recipe_collector.egg-info/dependency_links.txt
recipe_collector.egg-info/requires.txt
recipe_collector.egg-info/top_level.txt
recipe_collector/collectors/__init__.py
recipe_collector/collectors/html_collectors.py
recipe_collector/collectors/url_collectors/__init__.py
recipe_collector/collectors/url_collectors/food2fork.py
recipe_collector/parsers/__init__.py
recipe_collector/parsers/food2fork.py
recipe_collector/storage/__init__.py
recipe_collector/storage/csv.py
recipe_collector/storage/dynamodb.py
recipe_collector/storage/s3.py
recipe_collector/storage/text.py
recipe_collector/utils/__init__.py
recipe_collector/utils/decorators.py