Metadata-Version: 1.0
Name: recipe-collector
Version: 0.0.8
Summary: Collect and process recipes from various sources
Home-page: https://github.com/projectweekend/recipe-collector
Author: Brian Hines
Author-email: brian@projectweekend.net
License: MIT
Platform: UNKNOWN
